{
    "version": "https://jsonfeed.org/version/1",
    "title": "Sakura • All posts by \"雅思\" tag",
    "description": "一个专注于技术和思考分享的博客",
    "home_page_url": "https://sakurame.eu.org",
    "items": [
        {
            "id": "https://sakurame.eu.org/2023/07/09/basic-theory/%E9%9B%85%E6%80%9D%E5%A4%87%E8%80%83%E7%AC%94%E8%AE%B0%E6%95%B4%E7%90%86%E5%BD%92%E7%BA%B3%E9%95%BF%E6%9C%9F%E6%9B%B4%E6%96%B0%E7%89%88/",
            "url": "https://sakurame.eu.org/2023/07/09/basic-theory/%E9%9B%85%E6%80%9D%E5%A4%87%E8%80%83%E7%AC%94%E8%AE%B0%E6%95%B4%E7%90%86%E5%BD%92%E7%BA%B3%E9%95%BF%E6%9C%9F%E6%9B%B4%E6%96%B0%E7%89%88/",
            "title": "雅思备考笔记整理归纳长期更新版",
            "date_published": "2023-07-09T03:37:53.000Z",
            "content_html": "<p>对于这种含有<strong> than</strong> 或者<strong>形容词比较级</strong>的题目，必须在文章中对<strong>双方都进行讨论</strong>才能证明其中的某一方更......</p>\n<p>对于这种出现了诸如<strong> such as</strong> 等<strong>举出实例</strong>的考题，可以<strong>适当涉及</strong>其他实例，但是仍不要<strong>过多的偏离</strong> such as 所列举出的情况</p>\n<p>雅思听力只考 W 不考双写 U, 也就是 UU</p>\n",
            "tags": [
                "雅思"
            ]
        }
    ]
}